README.md
setup.py
bin/ppm
pip_ppm.egg-info/PKG-INFO
pip_ppm.egg-info/SOURCES.txt
pip_ppm.egg-info/dependency_links.txt
pip_ppm.egg-info/requires.txt
pip_ppm.egg-info/top_level.txt
ppm/__init__.py
ppm/command.py