Metadata-Version: 2.1
Name: pip-ppm
Version: 0.0.1
Summary: A pip alternative for managing python packages
Home-page: https://github.com/ekinertac/ppm
Author: Ekin Ertaç
Author-email: ekinertac@gmail.com
License: UNKNOWN
Platform: UNKNOWN
Classifier: Programming Language :: Python :: 3
Classifier: License :: OSI Approved :: MIT License
Classifier: Operating System :: OS Independent
Requires-Python: >=3.6
